neurocat/__init__.py
neurocat/reporter.py
neurocat/analyzers/__init__.py
neurocat/analyzers/ale.py
neurocat/analyzers/analyzer.py
neurocat/analyzers/confusion_matrix.py
neurocat/analyzers/counterfactual.py
neurocat/analyzers/mse.py
neurocat/models/__init__.py
neurocat/models/model.py
neurocat/models/tf.py
neurocat/models/torch.py
neurocat-0.0.1.dist-info/METADATA
neurocat-0.0.1.dist-info/WHEEL
neurocat-0.0.1.dist-info/top_level.txt
neurocat-0.0.1.dist-info/RECORD
