Metadata-Version: 2.1
Name: neurocat
Version: 0.0.1
Summary: Interface Design for Neurocat's Research Engineer Test
Home-page: UNKNOWN
Author: Christoper Glenn Wulur
Author-email: christoper.glennwu@gmail.com
License: UNKNOWN
Platform: UNKNOWN
Requires-Dist: absl-py (==0.11.0)
Requires-Dist: alibi (==0.5.6)
Requires-Dist: appnope (==0.1.2)
Requires-Dist: argon2-cffi (==20.1.0)
Requires-Dist: art (==5.1)
Requires-Dist: astroid (==2.5)
Requires-Dist: astunparse (==1.6.3)
Requires-Dist: async-generator (==1.10)
Requires-Dist: attrs (==20.3.0)
Requires-Dist: backcall (==0.2.0)
Requires-Dist: beautifulsoup4 (==4.9.3)
Requires-Dist: bleach (==3.3.0)
Requires-Dist: blis (==0.7.4)
Requires-Dist: cachetools (==4.2.1)
Requires-Dist: catalogue (==2.0.1)
Requires-Dist: certifi (==2020.12.5)
Requires-Dist: cffi (==1.14.5)
Requires-Dist: chardet (==4.0.0)
Requires-Dist: click (==7.1.2)
Requires-Dist: cycler (==0.10.0)
Requires-Dist: cymem (==2.0.5)
Requires-Dist: decorator (==4.4.2)
Requires-Dist: defusedxml (==0.6.0)
Requires-Dist: entrypoints (==0.3)
Requires-Dist: flatbuffers (==1.12)
Requires-Dist: gast (==0.3.3)
Requires-Dist: google-auth (==1.27.0)
Requires-Dist: google-auth-oauthlib (==0.4.2)
Requires-Dist: google-pasta (==0.2.0)
Requires-Dist: grpcio (==1.32.0)
Requires-Dist: h5py (==2.10.0)
Requires-Dist: idna (==2.10)
Requires-Dist: imageio (==2.9.0)
Requires-Dist: importlib-metadata (==3.4.0)
Requires-Dist: ipykernel (==5.5.0)
Requires-Dist: ipython (==7.20.0)
Requires-Dist: ipython-genutils (==0.2.0)
Requires-Dist: isort (==5.7.0)
Requires-Dist: jedi (==0.18.0)
Requires-Dist: Jinja2 (==2.11.3)
Requires-Dist: joblib (==1.0.1)
Requires-Dist: jsonschema (==3.2.0)
Requires-Dist: jupyter-client (==6.1.11)
Requires-Dist: jupyter-contrib-core (==0.3.3)
Requires-Dist: jupyter-contrib-nbextensions (==0.5.1)
Requires-Dist: jupyter-core (==4.7.1)
Requires-Dist: jupyter-highlight-selected-word (==0.2.0)
Requires-Dist: jupyter-latex-envs (==1.4.6)
Requires-Dist: jupyter-nbextensions-configurator (==0.4.1)
Requires-Dist: jupyterlab-pygments (==0.1.2)
Requires-Dist: Keras-Preprocessing (==1.1.2)
Requires-Dist: kiwisolver (==1.3.1)
Requires-Dist: lazy-object-proxy (==1.5.2)
Requires-Dist: llvmlite (==0.35.0)
Requires-Dist: lxml (==4.6.2)
Requires-Dist: Markdown (==3.3.3)
Requires-Dist: MarkupSafe (==1.1.1)
Requires-Dist: matplotlib (==3.3.4)
Requires-Dist: mccabe (==0.6.1)
Requires-Dist: mistune (==0.8.4)
Requires-Dist: murmurhash (==1.0.5)
Requires-Dist: nbclient (==0.5.3)
Requires-Dist: nbconvert (==6.0.7)
Requires-Dist: nbformat (==5.1.2)
Requires-Dist: nest-asyncio (==1.5.1)
Requires-Dist: networkx (==2.5)
Requires-Dist: notebook (==6.2.0)
Requires-Dist: numba (==0.52.0)
Requires-Dist: numpy (==1.19.5)
Requires-Dist: oauthlib (==3.1.0)
Requires-Dist: opt-einsum (==3.3.0)
Requires-Dist: packaging (==20.9)
Requires-Dist: pandas (==1.2.2)
Requires-Dist: pandocfilters (==1.4.3)
Requires-Dist: parso (==0.8.1)
Requires-Dist: pathy (==0.4.0)
Requires-Dist: pexpect (==4.8.0)
Requires-Dist: pickleshare (==0.7.5)
Requires-Dist: Pillow (==8.1.0)
Requires-Dist: preshed (==3.0.5)
Requires-Dist: prometheus-client (==0.9.0)
Requires-Dist: prompt-toolkit (==3.0.16)
Requires-Dist: protobuf (==3.15.1)
Requires-Dist: ptyprocess (==0.7.0)
Requires-Dist: pyasn1 (==0.4.8)
Requires-Dist: pyasn1-modules (==0.2.8)
Requires-Dist: pycm (==3.0)
Requires-Dist: pycparser (==2.20)
Requires-Dist: pydantic (==1.7.3)
Requires-Dist: Pygments (==2.8.0)
Requires-Dist: pylint (==2.7.1)
Requires-Dist: pyparsing (==2.4.7)
Requires-Dist: pyrsistent (==0.17.3)
Requires-Dist: python-dateutil (==2.8.1)
Requires-Dist: pytz (==2021.1)
Requires-Dist: PyWavelets (==1.1.1)
Requires-Dist: PyYAML (==5.4.1)
Requires-Dist: pyzmq (==22.0.3)
Requires-Dist: requests (==2.25.1)
Requires-Dist: requests-oauthlib (==1.3.0)
Requires-Dist: rsa (==4.7.1)
Requires-Dist: scikit-image (==0.18.1)
Requires-Dist: scikit-learn (==0.24.1)
Requires-Dist: scipy (==1.6.1)
Requires-Dist: seaborn (==0.11.1)
Requires-Dist: Send2Trash (==1.5.0)
Requires-Dist: shap (==0.37.0)
Requires-Dist: six (==1.15.0)
Requires-Dist: slicer (==0.0.3)
Requires-Dist: smart-open (==3.0.0)
Requires-Dist: soupsieve (==2.2)
Requires-Dist: spacy (==3.0.3)
Requires-Dist: spacy-legacy (==3.0.1)
Requires-Dist: spacy-lookups-data (==1.0.0)
Requires-Dist: srsly (==2.4.0)
Requires-Dist: tensorboard (==2.4.1)
Requires-Dist: tensorboard-plugin-wit (==1.8.0)
Requires-Dist: tensorflow (==2.4.1)
Requires-Dist: tensorflow-estimator (==2.4.0)
Requires-Dist: termcolor (==1.1.0)
Requires-Dist: terminado (==0.9.2)
Requires-Dist: testpath (==0.4.4)
Requires-Dist: thinc (==8.0.1)
Requires-Dist: threadpoolctl (==2.1.0)
Requires-Dist: tifffile (==2021.2.1)
Requires-Dist: toml (==0.10.2)
Requires-Dist: torch (==1.7.1)
Requires-Dist: torchvision (==0.8.2)
Requires-Dist: tornado (==6.1)
Requires-Dist: tqdm (==4.57.0)
Requires-Dist: traitlets (==5.0.5)
Requires-Dist: typed-ast (==1.4.2)
Requires-Dist: typer (==0.3.2)
Requires-Dist: typing-extensions (==3.7.4.3)
Requires-Dist: urllib3 (==1.26.3)
Requires-Dist: wasabi (==0.8.2)
Requires-Dist: wcwidth (==0.2.5)
Requires-Dist: webencodings (==0.5.1)
Requires-Dist: Werkzeug (==1.0.1)
Requires-Dist: wrapt (==1.12.1)
Requires-Dist: zipp (==3.4.0)
